setup.cfg
setup.py
examples/basic.py
livestat/__init__.py
livestat/incmoments.py
livestat/livestat.py
livestat.egg-info/PKG-INFO
livestat.egg-info/SOURCES.txt
livestat.egg-info/dependency_links.txt
livestat.egg-info/top_level.txt