Metadata-Version: 1.1
Name: livestat
Version: 0.1.1
Summary: Computing descriptive statistics over streaming data
Home-page: UNKNOWN
Author: Emanuele Ruffaldi
Author-email: emanuele.ruffaldi@gmail.com
License: BSD
Keywords: statistics kurtosis skewness live variance
Platform: UNKNOWN
Classifier: Development Status :: 4 - Beta
Classifier: Topic :: Scientific/Engineering :: Mathematics
Classifier: License :: OSI Approved :: Apache Software License
